vessel_BalticShipping/__init__.py
vessel_BalticShipping/vessel_BalticShipping.py
vessel_BalticShipping-1.12.dist-info/LICENSE
vessel_BalticShipping-1.12.dist-info/METADATA
vessel_BalticShipping-1.12.dist-info/WHEEL
vessel_BalticShipping-1.12.dist-info/top_level.txt
vessel_BalticShipping-1.12.dist-info/RECORD
