Metadata-Version: 2.1
Name: vessel-BalticShipping
Version: 1.12
Summary: Obtain Ship/ vessel data based on imo number
Home-page: https://www.linkedin.com/in/abhishek-venkatachalam-62121049/
Author: Abhishek Venkatachalam
Author-email: abhishek.venkatachalam06@gmail.com
License: GNU Affero General Public License v3.0
Keywords: Ship data,imo,vessel data,vessel imo gross tonnage data
Classifier: Development Status :: 4 - Beta
Classifier: Intended Audience :: Developers
Classifier: Topic :: Software Development :: Build Tools
Classifier: License :: OSI Approved :: GNU General Public License v3 or later (GPLv3+)
Classifier: Programming Language :: Python :: 3
Classifier: Programming Language :: Python :: 3.4
Classifier: Programming Language :: Python :: 3.5
Classifier: Programming Language :: Python :: 3.6
Requires-Python: >=3.7
License-File: LICENSE
Requires-Dist: requests
